{
  "cv_metrics": {
    "ic": 0.07119153202576413,
    "auc": 0.5181548003618038,
    "brier": 0.23580465858688596,
    "brier_raw": 0.2501738640739291,
    "hit_rate": 0.6055555555555555,
    "oos_rows": 180,
    "calibration": {
      "applied": true,
      "reason": "ok",
      "rows": 180,
      "brier_raw": 0.2501738640739291,
      "brier_cal": 0.23580465858688596
    },
    "reliability": [
      {
        "bin": 0,
        "lo": 0.0,
        "hi": 0.1,
        "count": 0,
        "mean_pred": null,
        "mean_obs": null
      },
      {
        "bin": 1,
        "lo": 0.1,
        "hi": 0.2,
        "count": 0,
        "mean_pred": null,
        "mean_obs": null
      },
      {
        "bin": 2,
        "lo": 0.2,
        "hi": 0.30000000000000004,
        "count": 19,
        "mean_pred": 0.26315789473684215,
        "mean_obs": 0.2631578947368421
      },
      {
        "bin": 3,
        "lo": 0.30000000000000004,
        "hi": 0.4,
        "count": 42,
        "mean_pred": 0.35714285714285715,
        "mean_obs": 0.35714285714285715
      },
      {
        "bin": 4,
        "lo": 0.4,
        "hi": 0.5,
        "count": 115,
        "mean_pred": 0.4260869565217389,
        "mean_obs": 0.4260869565217391
      },
      {
        "bin": 5,
        "lo": 0.5,
        "hi": 0.6000000000000001,
        "count": 4,
        "mean_pred": 0.5,
        "mean_obs": 0.5
      },
      {
        "bin": 6,
        "lo": 0.6000000000000001,
        "hi": 0.7000000000000001,
        "count": 0,
        "mean_pred": null,
        "mean_obs": null
      },
      {
        "bin": 7,
        "lo": 0.7000000000000001,
        "hi": 0.8,
        "count": 0,
        "mean_pred": null,
        "mean_obs": null
      },
      {
        "bin": 8,
        "lo": 0.8,
        "hi": 0.9,
        "count": 0,
        "mean_pred": null,
        "mean_obs": null
      },
      {
        "bin": 9,
        "lo": 0.9,
        "hi": 1.0,
        "count": 0,
        "mean_pred": null,
        "mean_obs": null
      }
    ]
  }
}