{
  "generated_at": "2026-04-06 21:43:42",
  "entries": [
    {
      "ticker": "6702.JP",
      "name": "富士通",
      "passed": false,
      "reason": "kpi_failed",
      "failures": [
        "cagr<3.0%",
        "expectancy<0.010%",
        "sharpe<0.20"
      ],
      "metrics": {
        "oos_days": 60,
        "trades": 13,
        "cagr": -0.22679029565121334,
        "max_drawdown": -0.11432272733530269,
        "sharpe": -1.3202684582423023,
        "expectancy": -0.005011513127487379,
        "turnover": 0.10833333333333334,
        "net_return_total": -0.05940185456058156
      },
      "metrics_tuning": {
        "oos_days": 120,
        "trades": 26,
        "cagr": -0.0026978717866600332,
        "max_drawdown": -0.03152946939268997,
        "sharpe": -0.024011227520888946,
        "expectancy": -0.0012472818289393803,
        "turnover": 0.10833333333333334,
        "net_return_total": -0.0012856098477981304
      },
      "metrics_holdout": {
        "oos_days": 60,
        "trades": 13,
        "cagr": -0.22679029565121334,
        "max_drawdown": -0.11432272733530269,
        "sharpe": -1.3202684582423023,
        "expectancy": -0.005011513127487379,
        "turnover": 0.10833333333333334,
        "net_return_total": -0.05940185456058156
      },
      "thresholds": {
        "buy": 0.7,
        "mild_buy": 0.55,
        "mild_sell": 0.2,
        "sell": 0.05,
        "volatility_limit": 0.03
      },
      "threshold_optimization": {
        "enabled": true,
        "optimized": true,
        "objective": "expectancy",
        "min_trades": 8,
        "candidate_count": 1134,
        "selection": "feasible_best",
        "selected_score": -0.0012472818289393803,
        "selected_trades": 26,
        "selected_metrics": {
          "oos_days": 120,
          "trades": 26,
          "cagr": -0.0026978717866600332,
          "max_drawdown": -0.03152946939268997,
          "sharpe": -0.024011227520888946,
          "expectancy": -0.0012472818289393803,
          "turnover": 0.10833333333333334,
          "net_return_total": -0.0012856098477981304
        },
        "data_split": "chronological_holdout",
        "tuning_rows": 120,
        "holdout_rows": 60,
        "holdout_used": true
      }
    },
    {
      "ticker": "4543.JP",
      "name": "テルモ",
      "passed": false,
      "reason": "kpi_failed",
      "failures": [
        "trades<10",
        "cagr<3.0%",
        "expectancy<0.010%",
        "sharpe<0.20"
      ],
      "metrics": {
        "oos_days": 60,
        "trades": 0,
        "cagr": 0.0,
        "max_drawdown": 0.0,
        "sharpe": 0.0,
        "expectancy": 0.0,
        "turnover": 0.0,
        "net_return_total": 0.0
      },
      "metrics_tuning": {
        "oos_days": 120,
        "trades": 10,
        "cagr": 0.06813509347995872,
        "max_drawdown": -0.009888411086483195,
        "sharpe": 1.1383229427839454,
        "expectancy": 0.0037760112305040504,
        "turnover": 0.041666666666666664,
        "net_return_total": 0.03188551515821425
      },
      "metrics_holdout": {
        "oos_days": 60,
        "trades": 0,
        "cagr": 0.0,
        "max_drawdown": 0.0,
        "sharpe": 0.0,
        "expectancy": 0.0,
        "turnover": 0.0,
        "net_return_total": 0.0
      },
      "thresholds": {
        "buy": 0.8,
        "mild_buy": 0.7,
        "mild_sell": 0.2,
        "sell": 0.05,
        "volatility_limit": 0.03
      },
      "threshold_optimization": {
        "enabled": true,
        "optimized": true,
        "objective": "expectancy",
        "min_trades": 8,
        "candidate_count": 1134,
        "selection": "feasible_best",
        "selected_score": 0.0037760112305040504,
        "selected_trades": 10,
        "selected_metrics": {
          "oos_days": 120,
          "trades": 10,
          "cagr": 0.06813509347995872,
          "max_drawdown": -0.009888411086483195,
          "sharpe": 1.1383229427839454,
          "expectancy": 0.0037760112305040504,
          "turnover": 0.041666666666666664,
          "net_return_total": 0.03188551515821425
        },
        "data_split": "chronological_holdout",
        "tuning_rows": 120,
        "holdout_rows": 60,
        "holdout_used": true
      }
    },
    {
      "ticker": "8591.JP",
      "name": "オリックス",
      "passed": false,
      "reason": "kpi_failed",
      "failures": [
        "cagr<3.0%",
        "expectancy<0.010%",
        "sharpe<0.20"
      ],
      "metrics": {
        "oos_days": 60,
        "trades": 19,
        "cagr": -0.12083398763908837,
        "max_drawdown": -0.07065723267857726,
        "sharpe": -1.1150879488845837,
        "expectancy": -0.002880168462929329,
        "turnover": 0.15833333333333333,
        "net_return_total": -0.03019695066565453
      },
      "metrics_tuning": {
        "oos_days": 120,
        "trades": 32,
        "cagr": 0.031019130109921855,
        "max_drawdown": -0.010393272828982836,
        "sharpe": 0.8945715739796767,
        "expectancy": -0.0002601810999269045,
        "turnover": 0.13333333333333333,
        "net_return_total": 0.014652868247933881
      },
      "metrics_holdout": {
        "oos_days": 60,
        "trades": 19,
        "cagr": -0.12083398763908837,
        "max_drawdown": -0.07065723267857726,
        "sharpe": -1.1150879488845837,
        "expectancy": -0.002880168462929329,
        "turnover": 0.15833333333333333,
        "net_return_total": -0.03019695066565453
      },
      "thresholds": {
        "buy": 0.7,
        "mild_buy": 0.55,
        "mild_sell": 0.2,
        "sell": 0.05,
        "volatility_limit": 0.03
      },
      "threshold_optimization": {
        "enabled": true,
        "optimized": true,
        "objective": "expectancy",
        "min_trades": 8,
        "candidate_count": 1134,
        "selection": "feasible_best",
        "selected_score": -0.0002601810999269045,
        "selected_trades": 32,
        "selected_metrics": {
          "oos_days": 120,
          "trades": 32,
          "cagr": 0.031019130109921855,
          "max_drawdown": -0.010393272828982836,
          "sharpe": 0.8945715739796767,
          "expectancy": -0.0002601810999269045,
          "turnover": 0.13333333333333333,
          "net_return_total": 0.014652868247933881
        },
        "data_split": "chronological_holdout",
        "tuning_rows": 120,
        "holdout_rows": 60,
        "holdout_used": true
      }
    },
    {
      "ticker": "1928.JP",
      "name": "積水ハウス",
      "passed": false,
      "reason": "kpi_failed",
      "failures": [
        "cagr<3.0%",
        "expectancy<0.010%",
        "sharpe<0.20"
      ],
      "metrics": {
        "oos_days": 60,
        "trades": 17,
        "cagr": -0.056347042669023795,
        "max_drawdown": -0.03294087791193068,
        "sharpe": -1.0731195608989594,
        "expectancy": -0.0018298096348350636,
        "turnover": 0.14166666666666666,
        "net_return_total": -0.013713860724503646
      },
      "metrics_tuning": {
        "oos_days": 120,
        "trades": 21,
        "cagr": 0.03688448556656887,
        "max_drawdown": -0.020781579879488477,
        "sharpe": 0.8287658533015818,
        "expectancy": -0.0006747462978777774,
        "turnover": 0.0875,
        "net_return_total": 0.017397474909722987
      },
      "metrics_holdout": {
        "oos_days": 60,
        "trades": 17,
        "cagr": -0.056347042669023795,
        "max_drawdown": -0.03294087791193068,
        "sharpe": -1.0731195608989594,
        "expectancy": -0.0018298096348350636,
        "turnover": 0.14166666666666666,
        "net_return_total": -0.013713860724503646
      },
      "thresholds": {
        "buy": 0.7,
        "mild_buy": 0.55,
        "mild_sell": 0.2,
        "sell": 0.05,
        "volatility_limit": 0.03
      },
      "threshold_optimization": {
        "enabled": true,
        "optimized": true,
        "objective": "expectancy",
        "min_trades": 8,
        "candidate_count": 1134,
        "selection": "feasible_best",
        "selected_score": -0.0006747462978777774,
        "selected_trades": 21,
        "selected_metrics": {
          "oos_days": 120,
          "trades": 21,
          "cagr": 0.03688448556656887,
          "max_drawdown": -0.020781579879488477,
          "sharpe": 0.8287658533015818,
          "expectancy": -0.0006747462978777774,
          "turnover": 0.0875,
          "net_return_total": 0.017397474909722987
        },
        "data_split": "chronological_holdout",
        "tuning_rows": 120,
        "holdout_rows": 60,
        "holdout_used": true
      }
    },
    {
      "ticker": "2802.JP",
      "name": "味の素",
      "passed": false,
      "reason": "kpi_failed",
      "failures": [
        "cagr<3.0%",
        "expectancy<0.010%",
        "sharpe<0.20"
      ],
      "metrics": {
        "oos_days": 60,
        "trades": 14,
        "cagr": -0.12489318253836035,
        "max_drawdown": -0.05517073899526925,
        "sharpe": -1.6673609917047714,
        "expectancy": -0.0029473715420076257,
        "turnover": 0.11666666666666667,
        "net_return_total": -0.03126494401946123
      },
      "metrics_tuning": {
        "oos_days": 120,
        "trades": 22,
        "cagr": 0.04028072598822563,
        "max_drawdown": -0.037191610241318784,
        "sharpe": 0.6335087126730818,
        "expectancy": -0.0005452107764323072,
        "turnover": 0.09166666666666666,
        "net_return_total": 0.01898297879461852
      },
      "metrics_holdout": {
        "oos_days": 60,
        "trades": 14,
        "cagr": -0.12489318253836035,
        "max_drawdown": -0.05517073899526925,
        "sharpe": -1.6673609917047714,
        "expectancy": -0.0029473715420076257,
        "turnover": 0.11666666666666667,
        "net_return_total": -0.03126494401946123
      },
      "thresholds": {
        "buy": 0.7,
        "mild_buy": 0.6,
        "mild_sell": 0.2,
        "sell": 0.05,
        "volatility_limit": 0.03
      },
      "threshold_optimization": {
        "enabled": true,
        "optimized": true,
        "objective": "expectancy",
        "min_trades": 8,
        "candidate_count": 1134,
        "selection": "feasible_best",
        "selected_score": -0.0005452107764323072,
        "selected_trades": 22,
        "selected_metrics": {
          "oos_days": 120,
          "trades": 22,
          "cagr": 0.04028072598822563,
          "max_drawdown": -0.037191610241318784,
          "sharpe": 0.6335087126730818,
          "expectancy": -0.0005452107764323072,
          "turnover": 0.09166666666666666,
          "net_return_total": 0.01898297879461852
        },
        "data_split": "chronological_holdout",
        "tuning_rows": 120,
        "holdout_rows": 60,
        "holdout_used": true
      }
    },
    {
      "ticker": "7751.JP",
      "name": "キヤノン",
      "passed": false,
      "reason": "kpi_failed",
      "failures": [
        "cagr<3.0%",
        "expectancy<0.010%",
        "sharpe<0.20"
      ],
      "metrics": {
        "oos_days": 60,
        "trades": 20,
        "cagr": -0.059983462098949336,
        "max_drawdown": -0.03862400807216093,
        "sharpe": -0.8529656679541605,
        "expectancy": -0.002099194916935895,
        "turnover": 0.16666666666666666,
        "net_return_total": -0.01462012285851344
      },
      "metrics_tuning": {
        "oos_days": 120,
        "trades": 22,
        "cagr": 0.1633189341623158,
        "max_drawdown": -0.012147822779919326,
        "sharpe": 2.8172504713240873,
        "expectancy": 0.0004189325957051153,
        "turnover": 0.09166666666666666,
        "net_return_total": 0.07469478461754586
      },
      "metrics_holdout": {
        "oos_days": 60,
        "trades": 20,
        "cagr": -0.059983462098949336,
        "max_drawdown": -0.03862400807216093,
        "sharpe": -0.8529656679541605,
        "expectancy": -0.002099194916935895,
        "turnover": 0.16666666666666666,
        "net_return_total": -0.01462012285851344
      },
      "thresholds": {
        "buy": 0.7,
        "mild_buy": 0.55,
        "mild_sell": 0.2,
        "sell": 0.05,
        "volatility_limit": 0.03
      },
      "threshold_optimization": {
        "enabled": true,
        "optimized": true,
        "objective": "expectancy",
        "min_trades": 8,
        "candidate_count": 1134,
        "selection": "feasible_best",
        "selected_score": 0.0004189325957051153,
        "selected_trades": 22,
        "selected_metrics": {
          "oos_days": 120,
          "trades": 22,
          "cagr": 0.1633189341623158,
          "max_drawdown": -0.012147822779919326,
          "sharpe": 2.8172504713240873,
          "expectancy": 0.0004189325957051153,
          "turnover": 0.09166666666666666,
          "net_return_total": 0.07469478461754586
        },
        "data_split": "chronological_holdout",
        "tuning_rows": 120,
        "holdout_rows": 60,
        "holdout_used": true
      }
    }
  ]
}