{"last_update": "2026-05-28 07:45:02", "tickers": {"7011.JP": {"ticker": "7011.JP", "name": "三菱重工業", "latest_data": {"date": "2026-05-27", "open": 4025.0, "high": 4050.0, "low": 3863.0, "close": 3898.0, "volume": 19574600, "ma_5": 3935.4, "ma_20": 4286.15, "ma_60": 4555.466666666666, "rsi": 19.376825705939623}, "avg_volume_20": 25864490.0, "latest_signal": {"ticker": "7011.JP", "name": "三菱重工業", "date": "2026-05-27", "close": 3898.0, "prob_up": 0.6672347498271078, "action": "HOLD", "reason": "自信なしのため見送り（過去検証で基準未達）", "limit_price": null, "stop_loss": null, "thresholds": {"buy": 0.7, "mild_buy": 0.6, "mild_sell": 0.2, "sell": 0.05, "volatility_limit": 0.03}, "threshold_optimization": {"enabled": true, "optimized": true, "objective": "expectancy", "min_trades": 8, "candidate_count": 1134, "selection": "feasible_best", "selected_score": 0.002678143369670452, "selected_trades": 18, "selected_metrics": {"oos_days": 120, "trades": 18, "cagr": 0.06282339602146325, "max_drawdown": -0.022085580715918818, "sharpe": 0.9363679191161922, "expectancy": 0.002678143369670452, "turnover": 0.075, "net_return_total": 0.029438785058881756}, "data_split": "chronological_holdout", "tuning_rows": 120, "holdout_rows": 60, "holdout_used": true}, "status": "ok", "raw_action": "MILD_BUY", "gate_passed": false, "confidence_label": "自信なし", "confidence_reason": "過去検証で基準未達 (expectancy<0.010%)"}, "data_file": "tickers/7011.JP.json", "rows": 500}, "6501.JP": {"ticker": "6501.JP", "name": "日立製作所", "latest_data": {"date": "2026-05-27", "open": 5100.0, "high": 5108.0, "low": 4955.0, "close": 4960.0, "volume": 10796000, "ma_5": 5039.0, "ma_20": 4947.0, "ma_60": 4908.1, "rsi": 54.74956822107082}, "avg_volume_20": 15382945.0, "latest_signal": {"ticker": "6501.JP", "name": "日立製作所", "date": "2026-05-27", "close": 4960.0, "prob_up": 0.4720494878881588, "action": "HOLD", "reason": "自信なしのため見送り（過去検証で基準未達）", "limit_price": null, "stop_loss": null, "thresholds": {"buy": 0.7, "mild_buy": 0.6, "mild_sell": 0.2, "sell": 0.05, "volatility_limit": 0.03}, "threshold_optimization": {"enabled": true, "optimized": true, "objective": "expectancy", "min_trades": 8, "candidate_count": 1134, "selection": "feasible_best", "selected_score": 0.0007180783793996615, "selected_trades": 8, "selected_metrics": {"oos_days": 120, "trades": 8, "cagr": 0.010313280092678623, "max_drawdown": -0.028380375857818274, "sharpe": 0.19935884598439063, "expectancy": 0.0007180783793996615, "turnover": 0.03333333333333333, "net_return_total": 0.004897889479928752}, "data_split": "chronological_holdout", "tuning_rows": 120, "holdout_rows": 60, "holdout_used": true}, "status": "ok", "raw_action": "HOLD", "gate_passed": false, "confidence_label": "自信なし", "confidence_reason": "過去検証で基準未達 (trades<10, cagr<3.0%, expectancy<0.010%, sharpe<0.20)"}, "data_file": "tickers/6501.JP.json", "rows": 500}, "6701.JP": {"ticker": "6701.JP", "name": "日本電気", "latest_data": {"date": "2026-05-27", "open": 4002.0, "high": 4154.0, "low": 4002.0, "close": 4146.0, "volume": 8303000, "ma_5": 4119.0, "ma_20": 4180.7, "ma_60": 4169.433333333333, "rsi": 55.50373134328358}, "avg_volume_20": 9553410.0, "latest_signal": {"ticker": "6701.JP", "name": "日本電気", "date": "2026-05-27", "close": 4146.0, "prob_up": 0.5822792248195519, "action": "HOLD", "reason": "自信なしのため見送り（過去検証で基準未達）", "limit_price": null, "stop_loss": null, "thresholds": {"buy": 0.8, "mild_buy": 0.65, "mild_sell": 0.25, "sell": 0.1, "volatility_limit": 0.04}, "threshold_optimization": {"enabled": true, "optimized": false, "objective": "expectancy", "min_trades": 8, "candidate_count": 1134, "selection": "feasible_best", "selected_score": 0.00635129351613866, "selected_trades": 11, "selected_metrics": {"oos_days": 120, "trades": 11, "cagr": 0.15089388941150084, "max_drawdown": -0.03661009636241941, "sharpe": 1.3079979834903523, "expectancy": 0.00635129351613866, "turnover": 0.04583333333333333, "net_return_total": 0.06921346919674365}, "data_split": "chronological_holdout", "tuning_rows": 120, "holdout_rows": 60, "holdout_used": true}, "status": "ok", "raw_action": "HOLD", "gate_passed": false, "confidence_label": "自信なし", "confidence_reason": "過去検証で基準未達 (trades<10, cagr<3.0%, expectancy<0.010%, sharpe<0.20)"}, "data_file": "tickers/6701.JP.json", "rows": 500}, "7013.JP": {"ticker": "7013.JP", "name": "IHI", "latest_data": {"date": "2026-05-27", "open": 2960.0, "high": 2978.0, "low": 2809.0, "close": 2818.0, "volume": 17678100, "ma_5": 2807.6, "ma_20": 2819.475, "ma_60": 3306.175, "rsi": 39.672429481346676}, "avg_volume_20": 24270130.0, "latest_signal": {"ticker": "7013.JP", "name": "IHI", "date": "2026-05-27", "close": 2818.0, "prob_up": 0.5461639645744543, "action": "HOLD", "reason": "自信なしのため見送り（過去検証で基準未達）", "limit_price": null, "stop_loss": null, "thresholds": {"buy": 0.7, "mild_buy": 0.6, "mild_sell": 0.2, "sell": 0.05, "volatility_limit": 0.03}, "threshold_optimization": {"enabled": true, "optimized": true, "objective": "expectancy", "min_trades": 8, "candidate_count": 1134, "selection": "feasible_best", "selected_score": -0.0007748690298541938, "selected_trades": 14, "selected_metrics": {"oos_days": 120, "trades": 14, "cagr": -0.040951236265030055, "max_drawdown": -0.024625478383207056, "sharpe": -0.6818410736278739, "expectancy": -0.0007748690298541938, "turnover": 0.058333333333333334, "net_return_total": -0.019714205035345156}, "data_split": "chronological_holdout", "tuning_rows": 120, "holdout_rows": 60, "holdout_used": true}, "status": "ok", "raw_action": "HOLD", "gate_passed": false, "confidence_label": "自信なし", "confidence_reason": "過去検証で基準未達 (cagr<3.0%, sharpe<0.20)"}, "data_file": "tickers/7013.JP.json", "rows": 500}, "6762.JP": {"ticker": "6762.JP", "name": "TDK", "latest_data": {"date": "2026-05-27", "open": 3750.0, "high": 3803.0, "low": 3608.0, "close": 3608.0, "volume": 15673600, "ma_5": 3492.2, "ma_20": 3040.775, "ma_60": 2492.4666666666667, "rsi": 77.61830876648565}, "avg_volume_20": 14543835.0, "latest_signal": {"ticker": "6762.JP", "name": "TDK", "date": "2026-05-27", "close": 3608.0, "prob_up": 0.4833700133744583, "action": "HOLD", "reason": "自信なしのため見送り（過去検証で基準未達）", "limit_price": null, "stop_loss": null, "thresholds": {"buy": 0.7, "mild_buy": 0.55, "mild_sell": 0.2, "sell": 0.05, "volatility_limit": 0.03}, "threshold_optimization": {"enabled": true, "optimized": true, "objective": "expectancy", "min_trades": 8, "candidate_count": 1134, "selection": "feasible_best", "selected_score": -0.0008917835937168393, "selected_trades": 32, "selected_metrics": {"oos_days": 120, "trades": 32, "cagr": 0.009529077321007051, "max_drawdown": -0.05107189445270832, "sharpe": 0.16504589591718766, "expectancy": -0.0008917835937168393, "turnover": 0.13333333333333333, "net_return_total": 0.004526385676678402}, "data_split": "chronological_holdout", "tuning_rows": 120, "holdout_rows": 60, "holdout_used": true}, "status": "ok", "raw_action": "HOLD", "gate_passed": false, "confidence_label": "自信なし", "confidence_reason": "過去検証で基準未達 (cagr<3.0%, expectancy<0.010%, sharpe<0.20)"}, "data_file": "tickers/6762.JP.json", "rows": 500}, "6723.JP": {"ticker": "6723.JP", "name": "ルネサスエレクトロニクス", "latest_data": {"date": "2026-05-27", "open": 4634.0, "high": 4689.0, "low": 4474.0, "close": 4474.0, "volume": 21999500, "ma_5": 4237.8, "ma_20": 3648.6, "ma_60": 2942.3416666666667, "rsi": 67.08149337615416}, "avg_volume_20": 21556805.0, "latest_signal": {"ticker": "6723.JP", "name": "ルネサスエレクトロニクス", "date": "2026-05-27", "close": 4474.0, "prob_up": 0.544629903158202, "action": "HOLD", "reason": "判断材料不足 (上昇確率 54%)", "limit_price": null, "stop_loss": null, "thresholds": {"buy": 0.7, "mild_buy": 0.55, "mild_sell": 0.2, "sell": 0.05, "volatility_limit": 0.03}, "threshold_optimization": {"enabled": true, "optimized": true, "objective": "expectancy", "min_trades": 8, "candidate_count": 1134, "selection": "feasible_best", "selected_score": 0.0024322769696650376, "selected_trades": 31, "selected_metrics": {"oos_days": 120, "trades": 31, "cagr": 0.26918718383778595, "max_drawdown": -0.01764623203456761, "sharpe": 2.4604096403977973, "expectancy": 0.0024322769696650376, "turnover": 0.12916666666666668, "net_return_total": 0.12020612227364813}, "data_split": "chronological_holdout", "tuning_rows": 120, "holdout_rows": 60, "holdout_used": true}, "status": "ok", "raw_action": "HOLD", "gate_passed": true, "confidence_label": "自信あり", "confidence_reason": "過去検証で基準をクリア"}, "data_file": "tickers/6723.JP.json", "rows": 500}, "6758.JP": {"ticker": "6758.JP", "name": "ソニーグループ", "latest_data": {"date": "2026-05-27", "open": 3492.0, "high": 3525.0, "low": 3448.0, "close": 3525.0, "volume": 17554500, "ma_5": 3550.0, "ma_20": 3416.1, "ma_60": 3369.75, "rsi": 64.15770609318997}, "avg_volume_20": 27977770.0, "latest_signal": {"ticker": "6758.JP", "name": "ソニーグループ", "date": "2026-05-27", "close": 3525.0, "prob_up": 0.514573514852255, "action": "HOLD", "reason": "自信なしのため見送り（過去検証で基準未達）", "limit_price": null, "stop_loss": null, "thresholds": {"buy": 0.7, "mild_buy": 0.55, "mild_sell": 0.2, "sell": 0.05, "volatility_limit": 0.03}, "threshold_optimization": {"enabled": true, "optimized": true, "objective": "expectancy", "min_trades": 8, "candidate_count": 1134, "selection": "feasible_best", "selected_score": -0.0011369214317950474, "selected_trades": 27, "selected_metrics": {"oos_days": 120, "trades": 27, "cagr": -0.09525215256191288, "max_drawdown": -0.07658131995101092, "sharpe": -1.4860541635972195, "expectancy": -0.0011369214317950474, "turnover": 0.1125, "net_return_total": -0.04654799273440091}, "data_split": "chronological_holdout", "tuning_rows": 120, "holdout_rows": 60, "holdout_used": true}, "status": "ok", "raw_action": "HOLD", "gate_passed": false, "confidence_label": "自信なし", "confidence_reason": "過去検証で基準未達 (expectancy<0.010%)"}, "data_file": "tickers/6758.JP.json", "rows": 500}, "1802.JP": {"ticker": "1802.JP", "name": "大林組", "latest_data": {"date": "2026-05-27", "open": 3441.0, "high": 3449.0, "low": 3318.0, "close": 3320.0, "volume": 2998600, "ma_5": 3289.8, "ma_20": 3544.65, "ma_60": 3759.4333333333334, "rsi": 33.674272226593246}, "avg_volume_20": 3585045.0, "latest_signal": {"ticker": "1802.JP", "name": "大林組", "date": "2026-05-27", "close": 3320.0, "prob_up": 0.5169266532255592, "action": "HOLD", "reason": "自信なしのため見送り（過去検証で基準未達）", "limit_price": null, "stop_loss": null, "thresholds": {"buy": 0.7, "mild_buy": 0.55, "mild_sell": 0.2, "sell": 0.05, "volatility_limit": 0.03}, "threshold_optimization": {"enabled": true, "optimized": true, "objective": "expectancy", "min_trades": 8, "candidate_count": 1134, "selection": "feasible_best", "selected_score": -0.00037672052068767525, "selected_trades": 38, "selected_metrics": {"oos_days": 120, "trades": 38, "cagr": 0.12804189164409996, "max_drawdown": -0.045603727951914586, "sharpe": 1.228743937796287, "expectancy": -0.00037672052068767525, "turnover": 0.15833333333333333, "net_return_total": 0.059050757809600674}, "data_split": "chronological_holdout", "tuning_rows": 120, "holdout_rows": 60, "holdout_used": true}, "status": "ok", "raw_action": "HOLD", "gate_passed": false, "confidence_label": "自信なし", "confidence_reason": "過去検証で基準未達 (cagr<3.0%, expectancy<0.010%, sharpe<0.20)"}, "data_file": "tickers/1802.JP.json", "rows": 500}}}